brynq_sdk_brynq/__init__.py
brynq_sdk_brynq/_scenario_parser.py
brynq_sdk_brynq/_scenario_transformer.py
brynq_sdk_brynq/brynq.py
brynq_sdk_brynq/credentials.py
brynq_sdk_brynq/customers.py
brynq_sdk_brynq/interfaces.py
brynq_sdk_brynq/mappings.py
brynq_sdk_brynq/organization_chart.py
brynq_sdk_brynq/roles.py
brynq_sdk_brynq/scenarios.py
brynq_sdk_brynq/source_systems.py
brynq_sdk_brynq/users.py
brynq_sdk_brynq/schemas/__init__.py
brynq_sdk_brynq/schemas/credentials.py
brynq_sdk_brynq/schemas/customers.py
brynq_sdk_brynq/schemas/interfaces.py
brynq_sdk_brynq/schemas/organization_chart.py
brynq_sdk_brynq/schemas/roles.py
brynq_sdk_brynq/schemas/scenarios.py
brynq_sdk_brynq/schemas/scenarios_parsed.py
brynq_sdk_brynq/schemas/users.py
brynq_sdk_brynq-4.2.2.dist-info/METADATA
brynq_sdk_brynq-4.2.2.dist-info/WHEEL
brynq_sdk_brynq-4.2.2.dist-info/top_level.txt
brynq_sdk_brynq-4.2.2.dist-info/RECORD
