Metadata-Version: 2.4
Name: brynq_sdk_brynq
Version: 4.2.2
Summary: BrynQ SDK for the BrynQ.com platform
Author: BrynQ
Author-email: support@brynq.com
License: BrynQ License
Requires-Dist: requests<=3,>=2
Requires-Dist: pydantic[email]
Dynamic: author
Dynamic: author-email
Dynamic: description
Dynamic: license
Dynamic: requires-dist
Dynamic: summary
